[
    {
        "product_name":"タガネ",
        "descriptions":[
            "石材や金属を割ったり削ったりするための鋭利な工具。",
            "ハンマーで叩きながら細かい形状加工ができる道具。",
            "固い素材を彫刻や整形する際に利用される専門的な工具。",
            "先端が硬く耐久性が高い、建築や石工で重宝される工具。"
        ]
    },
    {
        "product_name":"プーラー",
        "descriptions":[
            "固着した部品やベアリングを安全に外すための工具。",
            "車両整備や機械修理に便利な、爪付きの引き外し道具。",
            "簡単に力を加えて部品を分解できる、多用途な工具。",
            "精密な作業を助ける、固い接合部の取り外し専用工具。"
        ]
    },
    {
        "product_name":"サンドランマー",
        "descriptions":[
            "地面や砂型の密度を高めるために振動を利用する工具。",
            "砂や土をしっかりと締め固め、安定性を確保する道具。",
            "地盤の安定化や型枠内の材料圧縮に最適な振動型工具。",
            "振動と圧力を組み合わせて、均一な基盤形成を実現する道具。"
        ]
    },
    {
        "product_name":"スレッドタップ",
        "descriptions":[
            "ボルト用のねじ穴を正確に加工するための切削工具。",
            "金属やプラスチックにねじ山を形成する作業で使用する道具。",
            "精密なねじ穴作成や補修が可能な、多機能な工具。",
            "DIYから工業用途まで幅広く活躍する便利なねじ加工用工具。"
        ]
    },
    {
        "product_name":"ハトメパンチ",
        "descriptions":[
            "ハトメを簡単に取り付けられる、布や革用の加工工具。",
            "穴あけと金属リング取り付けを一度に行える便利な道具。",
            "バッグや文房具などの補強や装飾に使用される工具。",
            "金属部品を素材に取り付ける際の力加減が調整可能な工具。"
        ]
    },
    {
        "product_name":"スパデュラ",
        "descriptions":[
            "壁や家具の表面仕上げに用いる、薄いヘラ状の工具。",
            "塗料や接着剤を均一に伸ばす際に便利な道具。",
            "剥がれやすい素材の除去や整形作業を行うための工具。",
            "多用途に活用できる、柔軟性のある仕上げ用ヘラ。"
        ]
    },
    {
        "product_name":"タッカー",
        "descriptions":[
            "簡単に釘を打ち込める、強力な固定用工具。",
            "カーペットや布を効率よく固定する際に使用される道具。",
            "ポスターや内装作業で手軽に利用できる、小型の工具。",
            "手動またはエア式で操作できる、プロ仕様の固定工具。"
        ]
    },
    {
        "product_name":"ボルトクリッパー",
        "descriptions":[
            "太いボルトやワイヤーを切断するための強力な工具。",
            "固い金属を正確に切断できる、大型の切断道具。",
            "防犯チェーンや金属棒を簡単に処理するための工具。",
            "刃の耐久性が高く、長時間の使用にも耐える切断工具。"
        ]
    },
    {
        "product_name":"トルクレンチ",
        "descriptions":[
            "指定した力でボルトやナットを締め付けるための工具。",
            "過剰な締め付けを防ぎ、精密な作業を可能にする道具。",
            "自動車整備や工業製品の組み立てで使用される工具。",
            "ボルトの締め付け具合を視覚的に確認できる高性能工具。"
        ]
    },
    {
        "product_name":"リベットガン",
        "descriptions":[
            "リベットを使って金属やプラスチックを固定する工具。",
            "穴を開けずに材料をしっかりと接合するための道具。",
            "建築や家具製作で素早く接合作業を行うために便利な工具。",
            "小型で持ち運びやすく、作業効率を向上させる道具。"
        ]
    }
    ]